Metadata-Version: 1.1
Name: jsonhelper
Version: 0.0.8
Summary: JSON Tools
Home-page: https://github.com/alvarodeleon/jsontools
Author: Alvaro De Leon
Author-email: deleon@adl.com.uy
License: UNKNOWN
Download-URL: https://github.com/alvarodeleon/jsontools/tarball/0.0.8
Keywords: json
Platform: UNKNOWN
